opendp/whitenoise/__init__.py
opendp/whitenoise/core/__init__.py
opendp/whitenoise/core/api.py
opendp/whitenoise/core/api_pb2.py
opendp/whitenoise/core/base.py
opendp/whitenoise/core/base_pb2.py
opendp/whitenoise/core/components.py
opendp/whitenoise/core/components_pb2.py
opendp/whitenoise/core/value.py
opendp/whitenoise/core/value_pb2.py
opendp/whitenoise/core/variant_message_map.py
opendp/whitenoise/core/lib/libwhitenoise_ffi.dylib
opendp/whitenoise/core/lib/libwhitenoise_ffi.so
opendp_whitenoise_core-0.2.1.dist-info/LICENSE
opendp_whitenoise_core-0.2.1.dist-info/METADATA
opendp_whitenoise_core-0.2.1.dist-info/WHEEL
opendp_whitenoise_core-0.2.1.dist-info/top_level.txt
opendp_whitenoise_core-0.2.1.dist-info/RECORD
