Metadata-Version: 2.1
Name: opendp-whitenoise-core
Version: 0.2.1
Summary: a pluggable library of differentially private algorithms and mechanisms for releasing privacy preserving queries and statistics
Home-page: https://github.com/opendifferentialprivacy/whitenoise-core-python
Author: Consequences of Data
Author-email: whitenoise@opendp.io
License: UNKNOWN
Keywords: differential-privacy
Platform: any
Classifier: Development Status :: 3 - Alpha
Classifier: Intended Audience :: Developers
Classifier: Intended Audience :: Science/Research
Classifier: Operating System :: MacOS
Classifier: Operating System :: Microsoft :: Windows
Classifier: Operating System :: POSIX :: Linux
Classifier: Natural Language :: English
Classifier: Programming Language :: Python
Classifier: Programming Language :: Python :: 3
Classifier: Programming Language :: Python :: 3.6
Classifier: Programming Language :: Python :: 3.7
Classifier: Programming Language :: Python :: 3.8
Classifier: Programming Language :: Python :: 3.9
Classifier: Topic :: Scientific/Engineering
Requires-Python: >=3.6
Requires-Dist: protobuf
Requires-Dist: numpy
Provides-Extra: plotting
Requires-Dist: networkx ; extra == 'plotting'
Requires-Dist: matplotlib ; extra == 'plotting'
Provides-Extra: test
Requires-Dist: pytest (>=4.4.2) ; extra == 'test'
Requires-Dist: pandas (>=1.0.3) ; extra == 'test'
